calendly_fetcher/__init__.py
calendly_fetcher/calendly_fetcher.py
calendly_fetcher-0.1.2.dist-info/LICENSE
calendly_fetcher-0.1.2.dist-info/METADATA
calendly_fetcher-0.1.2.dist-info/WHEEL
calendly_fetcher-0.1.2.dist-info/top_level.txt
calendly_fetcher-0.1.2.dist-info/RECORD
