Metadata-Version: 2.1
Name: calendly-fetcher
Version: 0.1.2
Summary: A package to fetch availability data from Calendly
Home-page: https://github.com/malekinho8/calendly-fetcher.git
Author: Malek Ibrahim
Author-email: shmeek8@gmail.com
Classifier: Programming Language :: Python :: 3
Classifier: License :: OSI Approved :: MIT License
Classifier: Operating System :: OS Independent
Requires-Python: >=3.6
License-File: LICENSE
Requires-Dist: requests
